pript/__init__.py
pript/pript.py
pript-0.0.2.dist-info/LICENSE
pript-0.0.2.dist-info/METADATA
pript-0.0.2.dist-info/WHEEL
pript-0.0.2.dist-info/top_level.txt
pript-0.0.2.dist-info/RECORD
