Metadata-Version: 2.1
Name: pript
Version: 0.0.2
Summary: Print values to a stream, or to sys.stdout in the style of a receipt.
Author-email: Ash Bauer <devhalfbaked@gmail.com>
License: MIT License
Project-URL: Homepage, https://github.com/halfbakedbread/pript
Project-URL: Bug Reports, https://github.com/halfbakedbread/pript/issues
Project-URL: Source, https://github.com/halfbakedbread/pript/
Keywords: print,format,text,style,development
Classifier: Development Status :: 3 - Alpha
Classifier: Intended Audience :: Developers
Classifier: Topic :: Printing
Classifier: Topic :: Terminals
Classifier: Environment :: Console
Classifier: License :: OSI Approved :: MIT License
Classifier: Programming Language :: Python :: 3
Requires-Python: >=3
License-File: LICENSE
